TOPSISPANKAJ/__init__.py
TOPSISPANKAJ-0.1.dist-info/LICENSE.txt
TOPSISPANKAJ-0.1.dist-info/METADATA
TOPSISPANKAJ-0.1.dist-info/WHEEL
TOPSISPANKAJ-0.1.dist-info/top_level.txt
TOPSISPANKAJ-0.1.dist-info/RECORD
