Metadata-Version: 2.1
Name: TOPSISPANKAJ
Version: 0.1
Summary: Multiple Criteria Decision Making using Topsis
Home-page: UNKNOWN
Author: Pankaj Gupta
Author-email: pankaj140699@gmail.com
License: UNKNOWN
Platform: UNKNOWN
Requires-Dist: pandas
